yafem/__init__.py
yafem/json.py
yafem/model.py
yafem/nodes.py
yafem/simulation.py
yafem/elem/MCK.py
yafem/elem/__init__.py
yafem/elem/beam2d.py
yafem/elem/beam2d_cr.py
yafem/elem/beam2d_gen_func.py
yafem/elem/beam3d.py
yafem/elem/beam3d_circ_func.py
yafem/elem/beam3d_gen_func.py
yafem/elem/core_elem.py
yafem/elem/dev_tools.py
yafem/elem/fun_lambdify_saver.py
yafem/elem/plate_func.py
yafem/elem/shell4.py
yafem/elem/shell_func.py
yafem/elem/snapback.py
yafem/elem/snapback_func.py
yafem/elem/snapthrough.py
yafem/elem/snapthrough_func.py
yafem/elem/solid_func.py
yafem/elem/tet10.py
yafem/elem/tet10_func.py
yafem/elem/tri6.py
yafem/elem/tri6_func.py
yafem/elem/truss3d_ml.py
yafem/elem/truss3d_ml_func.py
yafem/elem/userdef.py
yafem-1.1.2.dist-info/licenses/LICENSE
yafem-1.1.2.dist-info/licenses/NOTICE
yafem-1.1.2.dist-info/METADATA
yafem-1.1.2.dist-info/WHEEL
yafem-1.1.2.dist-info/top_level.txt
yafem-1.1.2.dist-info/RECORD
