Metadata-Version: 2.4
Name: yafem
Version: 1.1.2
Summary: Yet Another Finite Element Method (YAFEM) Package
License: MIT
License-File: LICENSE
License-File: NOTICE
Requires-Dist: numpy
Requires-Dist: scipy
Requires-Dist: jax
Requires-Dist: jaxlib
Requires-Dist: matplotlib
Dynamic: description
Dynamic: license
Dynamic: license-file
Dynamic: requires-dist
Dynamic: summary
